deephaven/plugin/matplotlib/__init__.py
deephaven/plugin/matplotlib/_js_plugin.py
deephaven/plugin/matplotlib/_register.py
deephaven/plugin/matplotlib/deephaven.mplstyle
deephaven/plugin/matplotlib/figure_type.py
deephaven/plugin/matplotlib/_js/LICENSE
deephaven/plugin/matplotlib/_js/README.md
deephaven/plugin/matplotlib/_js/package.json
deephaven/plugin/matplotlib/_js/dist/index.js
deephaven_plugin_matplotlib-0.5.0.dist-info/LICENSE
deephaven_plugin_matplotlib-0.5.0.dist-info/METADATA
deephaven_plugin_matplotlib-0.5.0.dist-info/WHEEL
deephaven_plugin_matplotlib-0.5.0.dist-info/entry_points.txt
deephaven_plugin_matplotlib-0.5.0.dist-info/top_level.txt
deephaven_plugin_matplotlib-0.5.0.dist-info/RECORD
