Metadata-Version: 2.1
Name: deephaven-plugin-matplotlib
Version: 0.5.0
Summary: Deephaven Plugin for matplotlib
Home-page: https://github.com/deephaven/deephaven-plugins
Author: Devin Smith
Author-email: devinsmith@deephaven.io
Project-URL: Source Code, https://github.com/deephaven/deephaven-plugins
Project-URL: Bug Tracker, https://github.com/deephaven/deephaven-plugins/issues
Keywords: deephaven,plugin,matplotlib
Platform: any
Classifier: Programming Language :: Python :: 3
Classifier: License :: OSI Approved :: Apache Software License
Classifier: Operating System :: OS Independent
Classifier: Environment :: Plugins
Classifier: Framework :: Matplotlib
Classifier: Development Status :: 3 - Alpha
License-File: LICENSE
Requires-Dist: deephaven-core >=0.27.0
Requires-Dist: jpy >=0.14.0
Requires-Dist: deephaven-plugin >=0.5.0
Requires-Dist: matplotlib
Requires-Dist: deephaven-plugin-utilities
Provides-Extra: seaborn
Requires-Dist: seaborn >=0.13.0 ; extra == 'seaborn'
